{"d":{"results":[{"__metadata":{"id":"http://sapcmd02.retail.nrgenergy.com:8000/sap/opu/odata/sap/ZE_CCUX_CAMPAIGN_SRV/CpgChgOfferS(Contract='32253375',OfferCode='50056724',StartDate=datetime'2012-05-02T05%3A00%3A00')","uri":"http://sapcmd02.retail.nrgenergy.com:8000/sap/opu/odata/sap/ZE_CCUX_CAMPAIGN_SRV/CpgChgOfferS(Contract='32253375',OfferCode='50056724',StartDate=datetime'2012-05-02T05%3A00%3A00')","type":"ZE_CCUX_CAMPAIGN_OVW_SRV.Cpg"},"Contract":"32253375","OfferCode":"50056724","Type":"C","StartDate":"/Date(1335934800000)/","EndDate":"/Date(1351832400000)/","OfferTitle":"ZR_SAVE3 CNP AVG@2000=8.4 TS SECURE 6 20% WIND $0","Description":"me offer description for testing.","AvgUsage":"0","Campaign":"12A06R00V0","Promo":"WF3713","Term":"06","CncFee":"150.00","Incentive":"0.00","IncenDesc":"NO INCENTIVE","CurrInvAmt":"0.00","CurrCons":"0","EstInvAmt":"0.00","EstCents":"0.00","Disposition":"","LPcode":"","LPtext":"","LPReqName":"","EFLLevel":2000,"EFLPrice":"8.70","Brand":"RS","PromoRank":0,"EFLS":{"results":[{"__metadata":{"id":"http://sapcmd02.retail.nrgenergy.com:8000/sap/opu/odata/sap/ZE_CCUX_CAMPAIGN_SRV/EFLS(EFLType='BR',EFLLevel=500)","uri":"http://sapcmd02.retail.nrgenergy.com:8000/sap/opu/odata/sap/ZE_CCUX_CAMPAIGN_SRV/EFLS(EFLType='BR',EFLLevel=500)","type":"ZE_CCUX_CAMPAIGN_OVW_SRV.EFL"},"Contract":"32253375","OfferCode":"50056724","StartDate":"/Date(1335934800000)/","EFLType":"BR","EFLLevel":500,"EFLPrice":"10.00"},{"__metadata":{"id":"http://sapcmd02.retail.nrgenergy.com:8000/sap/opu/odata/sap/ZE_CCUX_CAMPAIGN_SRV/EFLS(EFLType='BR',EFLLevel=1000)","uri":"http://sapcmd02.retail.nrgenergy.com:8000/sap/opu/odata/sap/ZE_CCUX_CAMPAIGN_SRV/EFLS(EFLType='BR',EFLLevel=1000)","type":"ZE_CCUX_CAMPAIGN_OVW_SRV.EFL"},"Contract":"32253375","OfferCode":"50056724","StartDate":"/Date(1335934800000)/","EFLType":"BR","EFLLevel":1000,"EFLPrice":"9.10"},{"__metadata":{"id":"http://sapcmd02.retail.nrgenergy.com:8000/sap/opu/odata/sap/ZE_CCUX_CAMPAIGN_SRV/EFLS(EFLType='BR',EFLLevel=2000)","uri":"http://sapcmd02.retail.nrgenergy.com:8000/sap/opu/odata/sap/ZE_CCUX_CAMPAIGN_SRV/EFLS(EFLType='BR',EFLLevel=2000)","type":"ZE_CCUX_CAMPAIGN_OVW_SRV.EFL"},"Contract":"32253375","OfferCode":"50056724","StartDate":"/Date(1335934800000)/","EFLType":"BR","EFLLevel":2000,"EFLPrice":"8.70"}]},"Scripts":{"__deferred":{"uri":"http://sapcmd02.retail.nrgenergy.com:8000/sap/opu/odata/sap/ZE_CCUX_CAMPAIGN_SRV/CpgChgOfferS(Contract='32253375',OfferCode='50056724',StartDate=datetime'2012-05-02T05%3A00%3A00')/Scripts"}}},{"__metadata":{"id":"http://sapcmd02.retail.nrgenergy.com:8000/sap/opu/odata/sap/ZE_CCUX_CAMPAIGN_SRV/CpgChgOfferS(Contract='32253375',OfferCode='50160444',StartDate=datetime'2012-06-30T05%3A00%3A00')","uri":"http://sapcmd02.retail.nrgenergy.com:8000/sap/opu/odata/sap/ZE_CCUX_CAMPAIGN_SRV/CpgChgOfferS(Contract='32253375',OfferCode='50160444',StartDate=datetime'2012-06-30T05%3A00%3A00')","type":"ZE_CCUX_CAMPAIGN_OVW_SRV.Cpg"},"Contract":"32253375","OfferCode":"50160444","Type":"F","StartDate":"/Date(1341032400000)/","EndDate":"/Date(1358229600000)/","OfferTitle":"SAVE CPL AVG@2000 12.9 WPT SEC 6 NSP $0","Description":"- EFL Price: 500 kWh: 14.2 ¢/kWh,<BR/>1,000 kWh: 13.3 ¢/kWh,<BR/>2,000 kWh: 12.9 ¢/kWh<BR/>- EFL Prices include energy charge 8.3 ¢/kWh;<BR/>TDSP Delivery Charges and $0.00 Base Charge<BR/>- Recurring TDSP Delivery Charges of $9.63 per month<BR/>and 3.6945 ¢/kWh are passed through without mark-up<BR/>- Price security: price can change only to reflect actual price changes<BR/>that are allowed by Public Utility Commission rules due to changes in<BR/>law or regulatory charges after 10/14/2014","AvgUsage":"0","Campaign":"14K25R04C4","Promo":"XA1Q1B","Term":"00","CncFee":"100.00","Incentive":"0.00","IncenDesc":"NO INCENTIVE","CurrInvAmt":"0.00","CurrCons":"0","EstInvAmt":"0.00","EstCents":"0.00","Disposition":"","LPcode":"","LPtext":"","LPReqName":"","EFLLevel":2000,"EFLPrice":"12.90","Brand":"RE","PromoRank":7,"EFLS":{"results":[{"__metadata":{"id":"http://sapcmd02.retail.nrgenergy.com:8000/sap/opu/odata/sap/ZE_CCUX_CAMPAIGN_SRV/EFLS(EFLType='BR',EFLLevel=500)","uri":"http://sapcmd02.retail.nrgenergy.com:8000/sap/opu/odata/sap/ZE_CCUX_CAMPAIGN_SRV/EFLS(EFLType='BR',EFLLevel=500)","type":"ZE_CCUX_CAMPAIGN_OVW_SRV.EFL"},"Contract":"32253375","OfferCode":"50160444","StartDate":"/Date(1341032400000)/","EFLType":"BR","EFLLevel":500,"EFLPrice":"14.20"},{"__metadata":{"id":"http://sapcmd02.retail.nrgenergy.com:8000/sap/opu/odata/sap/ZE_CCUX_CAMPAIGN_SRV/EFLS(EFLType='BR',EFLLevel=1000)","uri":"http://sapcmd02.retail.nrgenergy.com:8000/sap/opu/odata/sap/ZE_CCUX_CAMPAIGN_SRV/EFLS(EFLType='BR',EFLLevel=1000)","type":"ZE_CCUX_CAMPAIGN_OVW_SRV.EFL"},"Contract":"32253375","OfferCode":"50160444","StartDate":"/Date(1341032400000)/","EFLType":"BR","EFLLevel":1000,"EFLPrice":"13.30"},{"__metadata":{"id":"http://sapcmd02.retail.nrgenergy.com:8000/sap/opu/odata/sap/ZE_CCUX_CAMPAIGN_SRV/EFLS(EFLType='BR',EFLLevel=2000)","uri":"http://sapcmd02.retail.nrgenergy.com:8000/sap/opu/odata/sap/ZE_CCUX_CAMPAIGN_SRV/EFLS(EFLType='BR',EFLLevel=2000)","type":"ZE_CCUX_CAMPAIGN_OVW_SRV.EFL"},"Contract":"32253375","OfferCode":"50160444","StartDate":"/Date(1341032400000)/","EFLType":"BR","EFLLevel":2000,"EFLPrice":"12.90"}]},"Scripts":{"__deferred":{"uri":"http://sapcmd02.retail.nrgenergy.com:8000/sap/opu/odata/sap/ZE_CCUX_CAMPAIGN_SRV/CpgChgOfferS(Contract='32253375',OfferCode='50160444',StartDate=datetime'2012-06-30T05%3A00%3A00')/Scripts"}}},{"__metadata":{"id":"http://sapcmd02.retail.nrgenergy.com:8000/sap/opu/odata/sap/ZE_CCUX_CAMPAIGN_SRV/CpgChgOfferS(Contract='32253375',OfferCode='50160100',StartDate=datetime'2012-06-30T05%3A00%3A00')","uri":"http://sapcmd02.retail.nrgenergy.com:8000/sap/opu/odata/sap/ZE_CCUX_CAMPAIGN_SRV/CpgChgOfferS(Contract='32253375',OfferCode='50160100',StartDate=datetime'2012-06-30T05%3A00%3A00')","type":"ZE_CCUX_CAMPAIGN_OVW_SRV.Cpg"},"Contract":"32253375","OfferCode":"50160100","Type":"P","StartDate":"/Date(1341032400000)/","EndDate":"/Date(1373864400000)/","OfferTitle":"CPL AVG@2000 13.9 SE N&W 12 WPT EML $0 NSP","Description":"-Reliant Keep Your Cash Nights and Weekends offers a discount<BR/>for all electricity used on nights and weekends included in the price.<BR/>- EFL Price: 500 kWh: 15.2 ¢/kWh,<BR/>1,000 kWh: 14.3 ¢/kWh,<BR/>2,000 kWh: 13.9 ¢/kWh<BR/>- EFL Prices include energy charge of 9.9 ¢/kWh,<BR/>TDSP delivery charges and any Base Charge<BR/>-Consumption from 8pm to 8am weekdays and all day on weekends will<BR/>get a discount of 1.0 ¢/kWh<BR/>-Nights and Weekends discount is reflected in the average price on your<BR/>monthly bill<BR/>-With this product you have access to the Weekly Summary email and<BR/>Online Account Management that provide insights into your consumption<BR/>-12 mo. term indexed product<BR/>-Indexed product prices are based on a formula provided in the<BR/>Electricity Facts Label, see EFL for details<BR/>-The pricing formula will not change for the duration of the<BR/>12 mo. term","AvgUsage":"0","Campaign":"14K25R04C2","Promo":"XA1PP7","Term":"00","CncFee":"150.00","Incentive":"0.00","IncenDesc":"NO INCENTIVE","CurrInvAmt":"0.00","CurrCons":"0","EstInvAmt":"0.00","EstCents":"0.00","Disposition":"","LPcode":"","LPtext":"","LPReqName":"","EFLLevel":2000,"EFLPrice":"13.90","Brand":"RE","PromoRank":1,"EFLS":{"results":[{"__metadata":{"id":"http://sapcmd02.retail.nrgenergy.com:8000/sap/opu/odata/sap/ZE_CCUX_CAMPAIGN_SRV/EFLS(EFLType='BR',EFLLevel=500)","uri":"http://sapcmd02.retail.nrgenergy.com:8000/sap/opu/odata/sap/ZE_CCUX_CAMPAIGN_SRV/EFLS(EFLType='BR',EFLLevel=500)","type":"ZE_CCUX_CAMPAIGN_OVW_SRV.EFL"},"Contract":"32253375","OfferCode":"50160100","StartDate":"/Date(1341032400000)/","EFLType":"BR","EFLLevel":500,"EFLPrice":"15.20"},{"__metadata":{"id":"http://sapcmd02.retail.nrgenergy.com:8000/sap/opu/odata/sap/ZE_CCUX_CAMPAIGN_SRV/EFLS(EFLType='BR',EFLLevel=1000)","uri":"http://sapcmd02.retail.nrgenergy.com:8000/sap/opu/odata/sap/ZE_CCUX_CAMPAIGN_SRV/EFLS(EFLType='BR',EFLLevel=1000)","type":"ZE_CCUX_CAMPAIGN_OVW_SRV.EFL"},"Contract":"32253375","OfferCode":"50160100","StartDate":"/Date(1341032400000)/","EFLType":"BR","EFLLevel":1000,"EFLPrice":"14.30"},{"__metadata":{"id":"http://sapcmd02.retail.nrgenergy.com:8000/sap/opu/odata/sap/ZE_CCUX_CAMPAIGN_SRV/EFLS(EFLType='BR',EFLLevel=2000)","uri":"http://sapcmd02.retail.nrgenergy.com:8000/sap/opu/odata/sap/ZE_CCUX_CAMPAIGN_SRV/EFLS(EFLType='BR',EFLLevel=2000)","type":"ZE_CCUX_CAMPAIGN_OVW_SRV.EFL"},"Contract":"32253375","OfferCode":"50160100","StartDate":"/Date(1341032400000)/","EFLType":"BR","EFLLevel":2000,"EFLPrice":"13.90"}]},"Scripts":{"__deferred":{"uri":"http://sapcmd02.retail.nrgenergy.com:8000/sap/opu/odata/sap/ZE_CCUX_CAMPAIGN_SRV/CpgChgOfferS(Contract='32253375',OfferCode='50160100',StartDate=datetime'2012-06-30T05%3A00%3A00')/Scripts"}}},{"__metadata":{"id":"http://sapcmd02.retail.nrgenergy.com:8000/sap/opu/odata/sap/ZE_CCUX_CAMPAIGN_SRV/CpgChgOfferS(Contract='32253375',OfferCode='50160120',StartDate=datetime'2012-06-30T05%3A00%3A00')","uri":"http://sapcmd02.retail.nrgenergy.com:8000/sap/opu/odata/sap/ZE_CCUX_CAMPAIGN_SRV/CpgChgOfferS(Contract='32253375',OfferCode='50160120',StartDate=datetime'2012-06-30T05%3A00%3A00')","type":"ZE_CCUX_CAMPAIGN_OVW_SRV.Cpg"},"Contract":"32253375","OfferCode":"50160120","Type":"R","StartDate":"/Date(1341032400000)/","EndDate":"/Date(253402236000000)/","OfferTitle":"DEFAULT ONLY - CPL SE N&W WPT MTM EML $0","Description":"-Reliant Keep Your Cash Nights and Weekends offers a discount<BR/>for all electricity used on nights and weekends included in the price.<BR/>- EFL Price: 500 kWh: 16.8 ¢/kWh,<BR/>1,000 kWh: 15.9 ¢/kWh,<BR/>2,000 kWh: 15.5 ¢/kWh<BR/>- EFL Prices include energy charge of 11.5 ¢/kWh,<BR/>TDSP delivery charges and any Base Charge<BR/>-Consumption from 8pm to 8am weekdays and all day on weekends will<BR/>get a discount of 1.0 ¢/kWh<BR/>-Nights and Weekends discount is reflected in the average price on your<BR/>monthly bill<BR/>-With this product you have access to the Weekly Summary email and<BR/>Online Account Management that provide insights into your consumption<BR/>-Month to month indexed product<BR/>-Indexed product prices are based on a formula provided in the<BR/>Electricity Facts Label, see EFL for details","AvgUsage":"0","Campaign":"14K25R04C2","Promo":"XA1PP7","Term":"00","CncFee":"295.00","Incentive":"0.00","IncenDesc":"NO INCENTIVE","CurrInvAmt":"0.00","CurrCons":"0","EstInvAmt":"0.00","EstCents":"0.00","Disposition":"","LPcode":"","LPtext":"","LPReqName":"","EFLLevel":2000,"EFLPrice":"15.50","Brand":"RE","PromoRank":2,"EFLS":{"results":[{"__metadata":{"id":"http://sapcmd02.retail.nrgenergy.com:8000/sap/opu/odata/sap/ZE_CCUX_CAMPAIGN_SRV/EFLS(EFLType='BR',EFLLevel=500)","uri":"http://sapcmd02.retail.nrgenergy.com:8000/sap/opu/odata/sap/ZE_CCUX_CAMPAIGN_SRV/EFLS(EFLType='BR',EFLLevel=500)","type":"ZE_CCUX_CAMPAIGN_OVW_SRV.EFL"},"Contract":"32253375","OfferCode":"50160120","StartDate":"/Date(1341032400000)/","EFLType":"BR","EFLLevel":500,"EFLPrice":"16.80"},{"__metadata":{"id":"http://sapcmd02.retail.nrgenergy.com:8000/sap/opu/odata/sap/ZE_CCUX_CAMPAIGN_SRV/EFLS(EFLType='BR',EFLLevel=1000)","uri":"http://sapcmd02.retail.nrgenergy.com:8000/sap/opu/odata/sap/ZE_CCUX_CAMPAIGN_SRV/EFLS(EFLType='BR',EFLLevel=1000)","type":"ZE_CCUX_CAMPAIGN_OVW_SRV.EFL"},"Contract":"32253375","OfferCode":"50160120","StartDate":"/Date(1341032400000)/","EFLType":"BR","EFLLevel":1000,"EFLPrice":"15.90"},{"__metadata":{"id":"http://sapcmd02.retail.nrgenergy.com:8000/sap/opu/odata/sap/ZE_CCUX_CAMPAIGN_SRV/EFLS(EFLType='BR',EFLLevel=2000)","uri":"http://sapcmd02.retail.nrgenergy.com:8000/sap/opu/odata/sap/ZE_CCUX_CAMPAIGN_SRV/EFLS(EFLType='BR',EFLLevel=2000)","type":"ZE_CCUX_CAMPAIGN_OVW_SRV.EFL"},"Contract":"32253375","OfferCode":"50160120","StartDate":"/Date(1341032400000)/","EFLType":"BR","EFLLevel":2000,"EFLPrice":"15.50"}]},"Scripts":{"__deferred":{"uri":"http://sapcmd02.retail.nrgenergy.com:8000/sap/opu/odata/sap/ZE_CCUX_CAMPAIGN_SRV/CpgChgOfferS(Contract='32253375',OfferCode='50160120',StartDate=datetime'2012-06-30T05%3A00%3A00')/Scripts"}}},{"__metadata":{"id":"http://sapcmd02.retail.nrgenergy.com:8000/sap/opu/odata/sap/ZE_CCUX_CAMPAIGN_SRV/CpgChgOfferS(Contract='32253375',OfferCode='50160442',StartDate=datetime'2012-06-30T05%3A00%3A00')","uri":"http://sapcmd02.retail.nrgenergy.com:8000/sap/opu/odata/sap/ZE_CCUX_CAMPAIGN_SRV/CpgChgOfferS(Contract='32253375',OfferCode='50160442',StartDate=datetime'2012-06-30T05%3A00%3A00')","type":"ZE_CCUX_CAMPAIGN_OVW_SRV.Cpg"},"Contract":"32253375","OfferCode":"50160442","Type":"R","StartDate":"/Date(1341032400000)/","EndDate":"/Date(1379221200000)/","OfferTitle":"CPL AVG@2000 13.5 WPT SEC 14 NSP $0","Description":"- EFL Price: 500 kWh: 14.8 ¢/kWh,<BR/>1,000 kWh: 13.9 ¢/kWh,<BR/>2,000 kWh: 13.5 ¢/kWh<BR/>- EFL Prices include energy charge 8.9 ¢/kWh;<BR/>TDSP Delivery Charges and $0.00 Base Charge<BR/>- Recurring TDSP Delivery Charges of $9.63 per month<BR/>and 3.6945 ¢/kWh are passed through without mark-up<BR/>- Price security: price can change only to reflect actual price changes<BR/>that are allowed by Public Utility Commission rules due to changes in<BR/>law or regulatory charges after 10/14/2014","AvgUsage":"0","Campaign":"14K25R04C2","Promo":"XA1PP7","Term":"00","CncFee":"200.00","Incentive":"0.00","IncenDesc":"NO INCENTIVE","CurrInvAmt":"0.00","CurrCons":"0","EstInvAmt":"0.00","EstCents":"0.00","Disposition":"","LPcode":"","LPtext":"","LPReqName":"","EFLLevel":2000,"EFLPrice":"13.50","Brand":"RE","PromoRank":3,"EFLS":{"results":[{"__metadata":{"id":"http://sapcmd02.retail.nrgenergy.com:8000/sap/opu/odata/sap/ZE_CCUX_CAMPAIGN_SRV/EFLS(EFLType='BR',EFLLevel=500)","uri":"http://sapcmd02.retail.nrgenergy.com:8000/sap/opu/odata/sap/ZE_CCUX_CAMPAIGN_SRV/EFLS(EFLType='BR',EFLLevel=500)","type":"ZE_CCUX_CAMPAIGN_OVW_SRV.EFL"},"Contract":"32253375","OfferCode":"50160442","StartDate":"/Date(1341032400000)/","EFLType":"BR","EFLLevel":500,"EFLPrice":"14.80"},{"__metadata":{"id":"http://sapcmd02.retail.nrgenergy.com:8000/sap/opu/odata/sap/ZE_CCUX_CAMPAIGN_SRV/EFLS(EFLType='BR',EFLLevel=1000)","uri":"http://sapcmd02.retail.nrgenergy.com:8000/sap/opu/odata/sap/ZE_CCUX_CAMPAIGN_SRV/EFLS(EFLType='BR',EFLLevel=1000)","type":"ZE_CCUX_CAMPAIGN_OVW_SRV.EFL"},"Contract":"32253375","OfferCode":"50160442","StartDate":"/Date(1341032400000)/","EFLType":"BR","EFLLevel":1000,"EFLPrice":"13.90"},{"__metadata":{"id":"http://sapcmd02.retail.nrgenergy.com:8000/sap/opu/odata/sap/ZE_CCUX_CAMPAIGN_SRV/EFLS(EFLType='BR',EFLLevel=2000)","uri":"http://sapcmd02.retail.nrgenergy.com:8000/sap/opu/odata/sap/ZE_CCUX_CAMPAIGN_SRV/EFLS(EFLType='BR',EFLLevel=2000)","type":"ZE_CCUX_CAMPAIGN_OVW_SRV.EFL"},"Contract":"32253375","OfferCode":"50160442","StartDate":"/Date(1341032400000)/","EFLType":"BR","EFLLevel":2000,"EFLPrice":"13.50"}]},"Scripts":{"__deferred":{"uri":"http://sapcmd02.retail.nrgenergy.com:8000/sap/opu/odata/sap/ZE_CCUX_CAMPAIGN_SRV/CpgChgOfferS(Contract='32253375',OfferCode='50160442',StartDate=datetime'2012-06-30T05%3A00%3A00')/Scripts"}}},{"__metadata":{"id":"http://sapcmd02.retail.nrgenergy.com:8000/sap/opu/odata/sap/ZE_CCUX_CAMPAIGN_SRV/CpgChgOfferS(Contract='32253375',OfferCode='50160142',StartDate=datetime'2012-06-30T05%3A00%3A00')","uri":"http://sapcmd02.retail.nrgenergy.com:8000/sap/opu/odata/sap/ZE_CCUX_CAMPAIGN_SRV/CpgChgOfferS(Contract='32253375',OfferCode='50160142',StartDate=datetime'2012-06-30T05%3A00%3A00')","type":"ZE_CCUX_CAMPAIGN_OVW_SRV.Cpg"},"Contract":"32253375","OfferCode":"50160142","Type":"R","StartDate":"/Date(1341032400000)/","EndDate":"/Date(1373864400000)/","OfferTitle":"CPL AVG@2000 13.9 SE FREE WEEKENDS 12 WPT $0 NSP","Description":"-Reliant Free Weekends plan offers a free energy charge for all<BR/>electricity used between 8pm Friday to 12am Monday.<BR/>- EFL Price: 500 kWh: 15.3 ¢/kWh,<BR/>1,000 kWh: 14.4 ¢/kWh,<BR/>2,000 kWh: 13.9 ¢/kWh<BR/>- EFL Prices include energy charge 13.7 ¢/kWh;<BR/>TDSP Delivery Charges and $0.00 Base Charge<BR/>- Free Weekend Energy Charge is reflected in the average price on your<BR/>monthly bill<BR/>-Requires a provisioned smart meter<BR/>-With this product you have access to the Weekly Summary email<BR/>and Online Account Management that provide insights into your<BR/>consumption<BR/>-12 mo. term indexed product<BR/>-Indexed product prices are based on a formula provided in the<BR/>Electricity Facts Label, see EFL for details<BR/>-The pricing formula will not change for the duration of the<BR/>12 mo. term","AvgUsage":"0","Campaign":"14K25R04C2","Promo":"XA1PP7","Term":"00","CncFee":"150.00","Incentive":"0.00","IncenDesc":"NO INCENTIVE","CurrInvAmt":"0.00","CurrCons":"0","EstInvAmt":"0.00","EstCents":"0.00","Disposition":"","LPcode":"","LPtext":"","LPReqName":"","EFLLevel":2000,"EFLPrice":"13.90","Brand":"RE","PromoRank":4,"EFLS":{"results":[{"__metadata":{"id":"http://sapcmd02.retail.nrgenergy.com:8000/sap/opu/odata/sap/ZE_CCUX_CAMPAIGN_SRV/EFLS(EFLType='BR',EFLLevel=500)","uri":"http://sapcmd02.retail.nrgenergy.com:8000/sap/opu/odata/sap/ZE_CCUX_CAMPAIGN_SRV/EFLS(EFLType='BR',EFLLevel=500)","type":"ZE_CCUX_CAMPAIGN_OVW_SRV.EFL"},"Contract":"32253375","OfferCode":"50160142","StartDate":"/Date(1341032400000)/","EFLType":"BR","EFLLevel":500,"EFLPrice":"15.30"},{"__metadata":{"id":"http://sapcmd02.retail.nrgenergy.com:8000/sap/opu/odata/sap/ZE_CCUX_CAMPAIGN_SRV/EFLS(EFLType='BR',EFLLevel=1000)","uri":"http://sapcmd02.retail.nrgenergy.com:8000/sap/opu/odata/sap/ZE_CCUX_CAMPAIGN_SRV/EFLS(EFLType='BR',EFLLevel=1000)","type":"ZE_CCUX_CAMPAIGN_OVW_SRV.EFL"},"Contract":"32253375","OfferCode":"50160142","StartDate":"/Date(1341032400000)/","EFLType":"BR","EFLLevel":1000,"EFLPrice":"14.40"},{"__metadata":{"id":"http://sapcmd02.retail.nrgenergy.com:8000/sap/opu/odata/sap/ZE_CCUX_CAMPAIGN_SRV/EFLS(EFLType='BR',EFLLevel=2000)","uri":"http://sapcmd02.retail.nrgenergy.com:8000/sap/opu/odata/sap/ZE_CCUX_CAMPAIGN_SRV/EFLS(EFLType='BR',EFLLevel=2000)","type":"ZE_CCUX_CAMPAIGN_OVW_SRV.EFL"},"Contract":"32253375","OfferCode":"50160142","StartDate":"/Date(1341032400000)/","EFLType":"BR","EFLLevel":2000,"EFLPrice":"13.90"}]},"Scripts":{"__deferred":{"uri":"http://sapcmd02.retail.nrgenergy.com:8000/sap/opu/odata/sap/ZE_CCUX_CAMPAIGN_SRV/CpgChgOfferS(Contract='32253375',OfferCode='50160142',StartDate=datetime'2012-06-30T05%3A00%3A00')/Scripts"}}},{"__metadata":{"id":"http://sapcmd02.retail.nrgenergy.com:8000/sap/opu/odata/sap/ZE_CCUX_CAMPAIGN_SRV/CpgChgOfferS(Contract='32253375',OfferCode='50160372',StartDate=datetime'2012-06-30T05%3A00%3A00')","uri":"http://sapcmd02.retail.nrgenergy.com:8000/sap/opu/odata/sap/ZE_CCUX_CAMPAIGN_SRV/CpgChgOfferS(Contract='32253375',OfferCode='50160372',StartDate=datetime'2012-06-30T05%3A00%3A00')","type":"ZE_CCUX_CAMPAIGN_OVW_SRV.Cpg"},"Contract":"32253375","OfferCode":"50160372","Type":"R","StartDate":"/Date(1341032400000)/","EndDate":"/Date(1405400400000)/","OfferTitle":"CPL AVG@2000 14.9 LEARNCONSERVE24 WPT $0 NSP","Description":"- EFL Price: 500 kWh: 17.0 ¢/kWh,<BR/>1,000 kWh: 15.6 ¢/kWh,<BR/>2,000 kWh: 14.9 ¢/kWh<BR/>- EFL Prices include energy charge 10.1 ¢/kWh;<BR/>TDSP Delivery Charges and $5.00 Base Charge<BR/>- Recurring TDSP Delivery Charges of $9.63 per month and<BR/>3.6945 ¢/kWh are passed through without mark-up<BR/>- TDSP Delivery Charges are effective as of 10/14/2014","AvgUsage":"0","Campaign":"14K25R04C2","Promo":"XA1PP7","Term":"00","CncFee":"295.00","Incentive":"0.00","IncenDesc":"NO INCENTIVE","CurrInvAmt":"0.00","CurrCons":"0","EstInvAmt":"0.00","EstCents":"0.00","Disposition":"","LPcode":"","LPtext":"","LPReqName":"","EFLLevel":2000,"EFLPrice":"14.90","Brand":"RE","PromoRank":5,"EFLS":{"results":[{"__metadata":{"id":"http://sapcmd02.retail.nrgenergy.com:8000/sap/opu/odata/sap/ZE_CCUX_CAMPAIGN_SRV/EFLS(EFLType='BR',EFLLevel=500)","uri":"http://sapcmd02.retail.nrgenergy.com:8000/sap/opu/odata/sap/ZE_CCUX_CAMPAIGN_SRV/EFLS(EFLType='BR',EFLLevel=500)","type":"ZE_CCUX_CAMPAIGN_OVW_SRV.EFL"},"Contract":"32253375","OfferCode":"50160372","StartDate":"/Date(1341032400000)/","EFLType":"BR","EFLLevel":500,"EFLPrice":"17.00"},{"__metadata":{"id":"http://sapcmd02.retail.nrgenergy.com:8000/sap/opu/odata/sap/ZE_CCUX_CAMPAIGN_SRV/EFLS(EFLType='BR',EFLLevel=1000)","uri":"http://sapcmd02.retail.nrgenergy.com:8000/sap/opu/odata/sap/ZE_CCUX_CAMPAIGN_SRV/EFLS(EFLType='BR',EFLLevel=1000)","type":"ZE_CCUX_CAMPAIGN_OVW_SRV.EFL"},"Contract":"32253375","OfferCode":"50160372","StartDate":"/Date(1341032400000)/","EFLType":"BR","EFLLevel":1000,"EFLPrice":"15.60"},{"__metadata":{"id":"http://sapcmd02.retail.nrgenergy.com:8000/sap/opu/odata/sap/ZE_CCUX_CAMPAIGN_SRV/EFLS(EFLType='BR',EFLLevel=2000)","uri":"http://sapcmd02.retail.nrgenergy.com:8000/sap/opu/odata/sap/ZE_CCUX_CAMPAIGN_SRV/EFLS(EFLType='BR',EFLLevel=2000)","type":"ZE_CCUX_CAMPAIGN_OVW_SRV.EFL"},"Contract":"32253375","OfferCode":"50160372","StartDate":"/Date(1341032400000)/","EFLType":"BR","EFLLevel":2000,"EFLPrice":"14.90"}]},"Scripts":{"__deferred":{"uri":"http://sapcmd02.retail.nrgenergy.com:8000/sap/opu/odata/sap/ZE_CCUX_CAMPAIGN_SRV/CpgChgOfferS(Contract='32253375',OfferCode='50160372',StartDate=datetime'2012-06-30T05%3A00%3A00')/Scripts"}}},{"__metadata":{"id":"http://sapcmd02.retail.nrgenergy.com:8000/sap/opu/odata/sap/ZE_CCUX_CAMPAIGN_SRV/CpgChgOfferS(Contract='32253375',OfferCode='50160443',StartDate=datetime'2012-06-30T05%3A00%3A00')","uri":"http://sapcmd02.retail.nrgenergy.com:8000/sap/opu/odata/sap/ZE_CCUX_CAMPAIGN_SRV/CpgChgOfferS(Contract='32253375',OfferCode='50160443',StartDate=datetime'2012-06-30T05%3A00%3A00')","type":"ZE_CCUX_CAMPAIGN_OVW_SRV.Cpg"},"Contract":"32253375","OfferCode":"50160443","Type":"S","StartDate":"/Date(1341032400000)/","EndDate":"/Date(1358229600000)/","OfferTitle":"SAVE CPL AVG@2000 13.3 WPT SEC 6 NSP $0","Description":"- EFL Price: 500 kWh: 14.6 ¢/kWh,<BR/>1,000 kWh: 13.7 ¢/kWh,<BR/>2,000 kWh: 13.3 ¢/kWh<BR/>- EFL Prices include energy charge 8.7 ¢/kWh;<BR/>TDSP Delivery Charges and $0.00 Base Charge<BR/>- Recurring TDSP Delivery Charges of $9.63 per month<BR/>and 3.6945 ¢/kWh are passed through without mark-up<BR/>- Price security: price can change only to reflect actual price changes<BR/>that are allowed by Public Utility Commission rules due to changes in<BR/>law or regulatory charges after 10/14/2014","AvgUsage":"0","Campaign":"14K25R04C4","Promo":"XA1PV9","Term":"00","CncFee":"75.00","Incentive":"0.00","IncenDesc":"NO INCENTIVE","CurrInvAmt":"0.00","CurrCons":"0","EstInvAmt":"0.00","EstCents":"0.00","Disposition":"","LPcode":"","LPtext":"","LPReqName":"","EFLLevel":2000,"EFLPrice":"13.30","Brand":"RE","PromoRank":6,"EFLS":{"results":[{"__metadata":{"id":"http://sapcmd02.retail.nrgenergy.com:8000/sap/opu/odata/sap/ZE_CCUX_CAMPAIGN_SRV/EFLS(EFLType='BR',EFLLevel=500)","uri":"http://sapcmd02.retail.nrgenergy.com:8000/sap/opu/odata/sap/ZE_CCUX_CAMPAIGN_SRV/EFLS(EFLType='BR',EFLLevel=500)","type":"ZE_CCUX_CAMPAIGN_OVW_SRV.EFL"},"Contract":"32253375","OfferCode":"50160443","StartDate":"/Date(1341032400000)/","EFLType":"BR","EFLLevel":500,"EFLPrice":"14.60"},{"__metadata":{"id":"http://sapcmd02.retail.nrgenergy.com:8000/sap/opu/odata/sap/ZE_CCUX_CAMPAIGN_SRV/EFLS(EFLType='BR',EFLLevel=1000)","uri":"http://sapcmd02.retail.nrgenergy.com:8000/sap/opu/odata/sap/ZE_CCUX_CAMPAIGN_SRV/EFLS(EFLType='BR',EFLLevel=1000)","type":"ZE_CCUX_CAMPAIGN_OVW_SRV.EFL"},"Contract":"32253375","OfferCode":"50160443","StartDate":"/Date(1341032400000)/","EFLType":"BR","EFLLevel":1000,"EFLPrice":"13.70"},{"__metadata":{"id":"http://sapcmd02.retail.nrgenergy.com:8000/sap/opu/odata/sap/ZE_CCUX_CAMPAIGN_SRV/EFLS(EFLType='BR',EFLLevel=2000)","uri":"http://sapcmd02.retail.nrgenergy.com:8000/sap/opu/odata/sap/ZE_CCUX_CAMPAIGN_SRV/EFLS(EFLType='BR',EFLLevel=2000)","type":"ZE_CCUX_CAMPAIGN_OVW_SRV.EFL"},"Contract":"32253375","OfferCode":"50160443","StartDate":"/Date(1341032400000)/","EFLType":"BR","EFLLevel":2000,"EFLPrice":"13.30"}]},"Scripts":{"__deferred":{"uri":"http://sapcmd02.retail.nrgenergy.com:8000/sap/opu/odata/sap/ZE_CCUX_CAMPAIGN_SRV/CpgChgOfferS(Contract='32253375',OfferCode='50160443',StartDate=datetime'2012-06-30T05%3A00%3A00')/Scripts"}}},{"__metadata":{"id":"http://sapcmd02.retail.nrgenergy.com:8000/sap/opu/odata/sap/ZE_CCUX_CAMPAIGN_SRV/CpgChgOfferS(Contract='32253375',OfferCode='50160100',StartDate=datetime'2015-10-05T05%3A00%3A00')","uri":"http://sapcmd02.retail.nrgenergy.com:8000/sap/opu/odata/sap/ZE_CCUX_CAMPAIGN_SRV/CpgChgOfferS(Contract='32253375',OfferCode='50160100',StartDate=datetime'2015-10-05T05%3A00%3A00')","type":"ZE_CCUX_CAMPAIGN_OVW_SRV.Cpg"},"Contract":"32253375","OfferCode":"50160100","Type":"SE","StartDate":"/Date(1444021200000)/","EndDate":"/Date(1373864400000)/","OfferTitle":"CPL AVG@2000 13.9 SE N&W 12 WPT EML $0 NSP","Description":"-Reliant Keep Your Cash Nights and Weekends offers a discount<BR/>for all electricity used on nights and weekends included in the price.<BR/>- EFL Price: 500 kWh: 15.2 ¢/kWh,<BR/>1,000 kWh: 14.3 ¢/kWh,<BR/>2,000 kWh: 13.9 ¢/kWh<BR/>- EFL Prices include energy charge of 9.9 ¢/kWh,<BR/>TDSP delivery charges and any Base Charge<BR/>-Consumption from 8pm to 8am weekdays and all day on weekends will<BR/>get a discount of 1.0 ¢/kWh<BR/>-Nights and Weekends discount is reflected in the average price on your<BR/>monthly bill<BR/>-With this product you have access to the Weekly Summary email and<BR/>Online Account Management that provide insights into your consumption<BR/>-12 mo. term indexed product<BR/>-Indexed product prices are based on a formula provided in the<BR/>Electricity Facts Label, see EFL for details<BR/>-The pricing formula will not change for the duration of the<BR/>12 mo. term","AvgUsage":"0","Campaign":"14K25R04C2","Promo":"XA1PP7","Term":"00","CncFee":"150.00","Incentive":"0.00","IncenDesc":"NO INCENTIVE","CurrInvAmt":"0.00","CurrCons":"0","EstInvAmt":"0.00","EstCents":"0.00","Disposition":"","LPcode":"","LPtext":"","LPReqName":"","EFLLevel":2000,"EFLPrice":"13.90","Brand":"","PromoRank":0,"EFLS":{"results":[{"__metadata":{"id":"http://sapcmd02.retail.nrgenergy.com:8000/sap/opu/odata/sap/ZE_CCUX_CAMPAIGN_SRV/EFLS(EFLType='BR',EFLLevel=500)","uri":"http://sapcmd02.retail.nrgenergy.com:8000/sap/opu/odata/sap/ZE_CCUX_CAMPAIGN_SRV/EFLS(EFLType='BR',EFLLevel=500)","type":"ZE_CCUX_CAMPAIGN_OVW_SRV.EFL"},"Contract":"32253375","OfferCode":"50160100","StartDate":"/Date(1444021200000)/","EFLType":"BR","EFLLevel":500,"EFLPrice":"15.20"},{"__metadata":{"id":"http://sapcmd02.retail.nrgenergy.com:8000/sap/opu/odata/sap/ZE_CCUX_CAMPAIGN_SRV/EFLS(EFLType='BR',EFLLevel=1000)","uri":"http://sapcmd02.retail.nrgenergy.com:8000/sap/opu/odata/sap/ZE_CCUX_CAMPAIGN_SRV/EFLS(EFLType='BR',EFLLevel=1000)","type":"ZE_CCUX_CAMPAIGN_OVW_SRV.EFL"},"Contract":"32253375","OfferCode":"50160100","StartDate":"/Date(1444021200000)/","EFLType":"BR","EFLLevel":1000,"EFLPrice":"14.30"},{"__metadata":{"id":"http://sapcmd02.retail.nrgenergy.com:8000/sap/opu/odata/sap/ZE_CCUX_CAMPAIGN_SRV/EFLS(EFLType='BR',EFLLevel=2000)","uri":"http://sapcmd02.retail.nrgenergy.com:8000/sap/opu/odata/sap/ZE_CCUX_CAMPAIGN_SRV/EFLS(EFLType='BR',EFLLevel=2000)","type":"ZE_CCUX_CAMPAIGN_OVW_SRV.EFL"},"Contract":"32253375","OfferCode":"50160100","StartDate":"/Date(1444021200000)/","EFLType":"BR","EFLLevel":2000,"EFLPrice":"13.90"}]},"Scripts":{"__deferred":{"uri":"http://sapcmd02.retail.nrgenergy.com:8000/sap/opu/odata/sap/ZE_CCUX_CAMPAIGN_SRV/CpgChgOfferS(Contract='32253375',OfferCode='50160100',StartDate=datetime'2015-10-05T05%3A00%3A00')/Scripts"}}},{"__metadata":{"id":"http://sapcmd02.retail.nrgenergy.com:8000/sap/opu/odata/sap/ZE_CCUX_CAMPAIGN_SRV/CpgChgOfferS(Contract='32253375',OfferCode='50160120',StartDate=datetime'2015-10-05T05%3A00%3A00')","uri":"http://sapcmd02.retail.nrgenergy.com:8000/sap/opu/odata/sap/ZE_CCUX_CAMPAIGN_SRV/CpgChgOfferS(Contract='32253375',OfferCode='50160120',StartDate=datetime'2015-10-05T05%3A00%3A00')","type":"ZE_CCUX_CAMPAIGN_OVW_SRV.Cpg"},"Contract":"32253375","OfferCode":"50160120","Type":"SE","StartDate":"/Date(1444021200000)/","EndDate":"/Date(253402236000000)/","OfferTitle":"DEFAULT ONLY - CPL SE N&W WPT MTM EML $0","Description":"-Reliant Keep Your Cash Nights and Weekends offers a discount<BR/>for all electricity used on nights and weekends included in the price.<BR/>- EFL Price: 500 kWh: 16.8 ¢/kWh,<BR/>1,000 kWh: 15.9 ¢/kWh,<BR/>2,000 kWh: 15.5 ¢/kWh<BR/>- EFL Prices include energy charge of 11.5 ¢/kWh,<BR/>TDSP delivery charges and any Base Charge<BR/>-Consumption from 8pm to 8am weekdays and all day on weekends will<BR/>get a discount of 1.0 ¢/kWh<BR/>-Nights and Weekends discount is reflected in the average price on your<BR/>monthly bill<BR/>-With this product you have access to the Weekly Summary email and<BR/>Online Account Management that provide insights into your consumption<BR/>-Month to month indexed product<BR/>-Indexed product prices are based on a formula provided in the<BR/>Electricity Facts Label, see EFL for details","AvgUsage":"0","Campaign":"14K25R04C2","Promo":"XA1PP7","Term":"00","CncFee":"295.00","Incentive":"0.00","IncenDesc":"NO INCENTIVE","CurrInvAmt":"0.00","CurrCons":"0","EstInvAmt":"0.00","EstCents":"0.00","Disposition":"","LPcode":"","LPtext":"","LPReqName":"","EFLLevel":2000,"EFLPrice":"15.50","Brand":"","PromoRank":0,"EFLS":{"results":[{"__metadata":{"id":"http://sapcmd02.retail.nrgenergy.com:8000/sap/opu/odata/sap/ZE_CCUX_CAMPAIGN_SRV/EFLS(EFLType='BR',EFLLevel=500)","uri":"http://sapcmd02.retail.nrgenergy.com:8000/sap/opu/odata/sap/ZE_CCUX_CAMPAIGN_SRV/EFLS(EFLType='BR',EFLLevel=500)","type":"ZE_CCUX_CAMPAIGN_OVW_SRV.EFL"},"Contract":"32253375","OfferCode":"50160120","StartDate":"/Date(1444021200000)/","EFLType":"BR","EFLLevel":500,"EFLPrice":"16.80"},{"__metadata":{"id":"http://sapcmd02.retail.nrgenergy.com:8000/sap/opu/odata/sap/ZE_CCUX_CAMPAIGN_SRV/EFLS(EFLType='BR',EFLLevel=1000)","uri":"http://sapcmd02.retail.nrgenergy.com:8000/sap/opu/odata/sap/ZE_CCUX_CAMPAIGN_SRV/EFLS(EFLType='BR',EFLLevel=1000)","type":"ZE_CCUX_CAMPAIGN_OVW_SRV.EFL"},"Contract":"32253375","OfferCode":"50160120","StartDate":"/Date(1444021200000)/","EFLType":"BR","EFLLevel":1000,"EFLPrice":"15.90"},{"__metadata":{"id":"http://sapcmd02.retail.nrgenergy.com:8000/sap/opu/odata/sap/ZE_CCUX_CAMPAIGN_SRV/EFLS(EFLType='BR',EFLLevel=2000)","uri":"http://sapcmd02.retail.nrgenergy.com:8000/sap/opu/odata/sap/ZE_CCUX_CAMPAIGN_SRV/EFLS(EFLType='BR',EFLLevel=2000)","type":"ZE_CCUX_CAMPAIGN_OVW_SRV.EFL"},"Contract":"32253375","OfferCode":"50160120","StartDate":"/Date(1444021200000)/","EFLType":"BR","EFLLevel":2000,"EFLPrice":"15.50"}]},"Scripts":{"__deferred":{"uri":"http://sapcmd02.retail.nrgenergy.com:8000/sap/opu/odata/sap/ZE_CCUX_CAMPAIGN_SRV/CpgChgOfferS(Contract='32253375',OfferCode='50160120',StartDate=datetime'2015-10-05T05%3A00%3A00')/Scripts"}}},{"__metadata":{"id":"http://sapcmd02.retail.nrgenergy.com:8000/sap/opu/odata/sap/ZE_CCUX_CAMPAIGN_SRV/CpgChgOfferS(Contract='32253375',OfferCode='50160142',StartDate=datetime'2015-10-05T05%3A00%3A00')","uri":"http://sapcmd02.retail.nrgenergy.com:8000/sap/opu/odata/sap/ZE_CCUX_CAMPAIGN_SRV/CpgChgOfferS(Contract='32253375',OfferCode='50160142',StartDate=datetime'2015-10-05T05%3A00%3A00')","type":"ZE_CCUX_CAMPAIGN_OVW_SRV.Cpg"},"Contract":"32253375","OfferCode":"50160142","Type":"SE","StartDate":"/Date(1444021200000)/","EndDate":"/Date(1373864400000)/","OfferTitle":"CPL AVG@2000 13.9 SE FREE WEEKENDS 12 WPT $0 NSP","Description":"-Reliant Free Weekends plan offers a free energy charge for all<BR/>electricity used between 8pm Friday to 12am Monday.<BR/>- EFL Price: 500 kWh: 15.3 ¢/kWh,<BR/>1,000 kWh: 14.4 ¢/kWh,<BR/>2,000 kWh: 13.9 ¢/kWh<BR/>- EFL Prices include energy charge 13.7 ¢/kWh;<BR/>TDSP Delivery Charges and $0.00 Base Charge<BR/>- Free Weekend Energy Charge is reflected in the average price on your<BR/>monthly bill<BR/>-Requires a provisioned smart meter<BR/>-With this product you have access to the Weekly Summary email<BR/>and Online Account Management that provide insights into your<BR/>consumption<BR/>-12 mo. term indexed product<BR/>-Indexed product prices are based on a formula provided in the<BR/>Electricity Facts Label, see EFL for details<BR/>-The pricing formula will not change for the duration of the<BR/>12 mo. term","AvgUsage":"0","Campaign":"14K25R04C2","Promo":"XA1PP7","Term":"00","CncFee":"150.00","Incentive":"0.00","IncenDesc":"NO INCENTIVE","CurrInvAmt":"0.00","CurrCons":"0","EstInvAmt":"0.00","EstCents":"0.00","Disposition":"","LPcode":"","LPtext":"","LPReqName":"","EFLLevel":2000,"EFLPrice":"13.90","Brand":"","PromoRank":0,"EFLS":{"results":[{"__metadata":{"id":"http://sapcmd02.retail.nrgenergy.com:8000/sap/opu/odata/sap/ZE_CCUX_CAMPAIGN_SRV/EFLS(EFLType='BR',EFLLevel=500)","uri":"http://sapcmd02.retail.nrgenergy.com:8000/sap/opu/odata/sap/ZE_CCUX_CAMPAIGN_SRV/EFLS(EFLType='BR',EFLLevel=500)","type":"ZE_CCUX_CAMPAIGN_OVW_SRV.EFL"},"Contract":"32253375","OfferCode":"50160142","StartDate":"/Date(1444021200000)/","EFLType":"BR","EFLLevel":500,"EFLPrice":"15.30"},{"__metadata":{"id":"http://sapcmd02.retail.nrgenergy.com:8000/sap/opu/odata/sap/ZE_CCUX_CAMPAIGN_SRV/EFLS(EFLType='BR',EFLLevel=1000)","uri":"http://sapcmd02.retail.nrgenergy.com:8000/sap/opu/odata/sap/ZE_CCUX_CAMPAIGN_SRV/EFLS(EFLType='BR',EFLLevel=1000)","type":"ZE_CCUX_CAMPAIGN_OVW_SRV.EFL"},"Contract":"32253375","OfferCode":"50160142","StartDate":"/Date(1444021200000)/","EFLType":"BR","EFLLevel":1000,"EFLPrice":"14.40"},{"__metadata":{"id":"http://sapcmd02.retail.nrgenergy.com:8000/sap/opu/odata/sap/ZE_CCUX_CAMPAIGN_SRV/EFLS(EFLType='BR',EFLLevel=2000)","uri":"http://sapcmd02.retail.nrgenergy.com:8000/sap/opu/odata/sap/ZE_CCUX_CAMPAIGN_SRV/EFLS(EFLType='BR',EFLLevel=2000)","type":"ZE_CCUX_CAMPAIGN_OVW_SRV.EFL"},"Contract":"32253375","OfferCode":"50160142","StartDate":"/Date(1444021200000)/","EFLType":"BR","EFLLevel":2000,"EFLPrice":"13.90"}]},"Scripts":{"__deferred":{"uri":"http://sapcmd02.retail.nrgenergy.com:8000/sap/opu/odata/sap/ZE_CCUX_CAMPAIGN_SRV/CpgChgOfferS(Contract='32253375',OfferCode='50160142',StartDate=datetime'2015-10-05T05%3A00%3A00')/Scripts"}}},{"__metadata":{"id":"http://sapcmd02.retail.nrgenergy.com:8000/sap/opu/odata/sap/ZE_CCUX_CAMPAIGN_SRV/CpgChgOfferS(Contract='32253375',OfferCode='50160372',StartDate=datetime'2015-10-05T05%3A00%3A00')","uri":"http://sapcmd02.retail.nrgenergy.com:8000/sap/opu/odata/sap/ZE_CCUX_CAMPAIGN_SRV/CpgChgOfferS(Contract='32253375',OfferCode='50160372',StartDate=datetime'2015-10-05T05%3A00%3A00')","type":"ZE_CCUX_CAMPAIGN_OVW_SRV.Cpg"},"Contract":"32253375","OfferCode":"50160372","Type":"SE","StartDate":"/Date(1444021200000)/","EndDate":"/Date(1405400400000)/","OfferTitle":"CPL AVG@2000 14.9 LEARNCONSERVE24 WPT $0 NSP","Description":"- EFL Price: 500 kWh: 17.0 ¢/kWh,<BR/>1,000 kWh: 15.6 ¢/kWh,<BR/>2,000 kWh: 14.9 ¢/kWh<BR/>- EFL Prices include energy charge 10.1 ¢/kWh;<BR/>TDSP Delivery Charges and $5.00 Base Charge<BR/>- Recurring TDSP Delivery Charges of $9.63 per month and<BR/>3.6945 ¢/kWh are passed through without mark-up<BR/>- TDSP Delivery Charges are effective as of 10/14/2014","AvgUsage":"0","Campaign":"14K25R04C2","Promo":"XA1PP7","Term":"00","CncFee":"295.00","Incentive":"0.00","IncenDesc":"NO INCENTIVE","CurrInvAmt":"0.00","CurrCons":"0","EstInvAmt":"0.00","EstCents":"0.00","Disposition":"","LPcode":"","LPtext":"","LPReqName":"","EFLLevel":2000,"EFLPrice":"14.90","Brand":"","PromoRank":0,"EFLS":{"results":[{"__metadata":{"id":"http://sapcmd02.retail.nrgenergy.com:8000/sap/opu/odata/sap/ZE_CCUX_CAMPAIGN_SRV/EFLS(EFLType='BR',EFLLevel=500)","uri":"http://sapcmd02.retail.nrgenergy.com:8000/sap/opu/odata/sap/ZE_CCUX_CAMPAIGN_SRV/EFLS(EFLType='BR',EFLLevel=500)","type":"ZE_CCUX_CAMPAIGN_OVW_SRV.EFL"},"Contract":"32253375","OfferCode":"50160372","StartDate":"/Date(1444021200000)/","EFLType":"BR","EFLLevel":500,"EFLPrice":"17.00"},{"__metadata":{"id":"http://sapcmd02.retail.nrgenergy.com:8000/sap/opu/odata/sap/ZE_CCUX_CAMPAIGN_SRV/EFLS(EFLType='BR',EFLLevel=1000)","uri":"http://sapcmd02.retail.nrgenergy.com:8000/sap/opu/odata/sap/ZE_CCUX_CAMPAIGN_SRV/EFLS(EFLType='BR',EFLLevel=1000)","type":"ZE_CCUX_CAMPAIGN_OVW_SRV.EFL"},"Contract":"32253375","OfferCode":"50160372","StartDate":"/Date(1444021200000)/","EFLType":"BR","EFLLevel":1000,"EFLPrice":"15.60"},{"__metadata":{"id":"http://sapcmd02.retail.nrgenergy.com:8000/sap/opu/odata/sap/ZE_CCUX_CAMPAIGN_SRV/EFLS(EFLType='BR',EFLLevel=2000)","uri":"http://sapcmd02.retail.nrgenergy.com:8000/sap/opu/odata/sap/ZE_CCUX_CAMPAIGN_SRV/EFLS(EFLType='BR',EFLLevel=2000)","type":"ZE_CCUX_CAMPAIGN_OVW_SRV.EFL"},"Contract":"32253375","OfferCode":"50160372","StartDate":"/Date(1444021200000)/","EFLType":"BR","EFLLevel":2000,"EFLPrice":"14.90"}]},"Scripts":{"__deferred":{"uri":"http://sapcmd02.retail.nrgenergy.com:8000/sap/opu/odata/sap/ZE_CCUX_CAMPAIGN_SRV/CpgChgOfferS(Contract='32253375',OfferCode='50160372',StartDate=datetime'2015-10-05T05%3A00%3A00')/Scripts"}}},{"__metadata":{"id":"http://sapcmd02.retail.nrgenergy.com:8000/sap/opu/odata/sap/ZE_CCUX_CAMPAIGN_SRV/CpgChgOfferS(Contract='32253375',OfferCode='50160442',StartDate=datetime'2015-10-05T05%3A00%3A00')","uri":"http://sapcmd02.retail.nrgenergy.com:8000/sap/opu/odata/sap/ZE_CCUX_CAMPAIGN_SRV/CpgChgOfferS(Contract='32253375',OfferCode='50160442',StartDate=datetime'2015-10-05T05%3A00%3A00')","type":"ZE_CCUX_CAMPAIGN_OVW_SRV.Cpg"},"Contract":"32253375","OfferCode":"50160442","Type":"SE","StartDate":"/Date(1444021200000)/","EndDate":"/Date(1379221200000)/","OfferTitle":"CPL AVG@2000 13.5 WPT SEC 14 NSP $0","Description":"- EFL Price: 500 kWh: 14.8 ¢/kWh,<BR/>1,000 kWh: 13.9 ¢/kWh,<BR/>2,000 kWh: 13.5 ¢/kWh<BR/>- EFL Prices include energy charge 8.9 ¢/kWh;<BR/>TDSP Delivery Charges and $0.00 Base Charge<BR/>- Recurring TDSP Delivery Charges of $9.63 per month<BR/>and 3.6945 ¢/kWh are passed through without mark-up<BR/>- Price security: price can change only to reflect actual price changes<BR/>that are allowed by Public Utility Commission rules due to changes in<BR/>law or regulatory charges after 10/14/2014","AvgUsage":"0","Campaign":"14K25R04C2","Promo":"XA1PP7","Term":"00","CncFee":"200.00","Incentive":"0.00","IncenDesc":"NO INCENTIVE","CurrInvAmt":"0.00","CurrCons":"0","EstInvAmt":"0.00","EstCents":"0.00","Disposition":"","LPcode":"","LPtext":"","LPReqName":"","EFLLevel":2000,"EFLPrice":"13.50","Brand":"","PromoRank":0,"EFLS":{"results":[{"__metadata":{"id":"http://sapcmd02.retail.nrgenergy.com:8000/sap/opu/odata/sap/ZE_CCUX_CAMPAIGN_SRV/EFLS(EFLType='BR',EFLLevel=500)","uri":"http://sapcmd02.retail.nrgenergy.com:8000/sap/opu/odata/sap/ZE_CCUX_CAMPAIGN_SRV/EFLS(EFLType='BR',EFLLevel=500)","type":"ZE_CCUX_CAMPAIGN_OVW_SRV.EFL"},"Contract":"32253375","OfferCode":"50160442","StartDate":"/Date(1444021200000)/","EFLType":"BR","EFLLevel":500,"EFLPrice":"14.80"},{"__metadata":{"id":"http://sapcmd02.retail.nrgenergy.com:8000/sap/opu/odata/sap/ZE_CCUX_CAMPAIGN_SRV/EFLS(EFLType='BR',EFLLevel=1000)","uri":"http://sapcmd02.retail.nrgenergy.com:8000/sap/opu/odata/sap/ZE_CCUX_CAMPAIGN_SRV/EFLS(EFLType='BR',EFLLevel=1000)","type":"ZE_CCUX_CAMPAIGN_OVW_SRV.EFL"},"Contract":"32253375","OfferCode":"50160442","StartDate":"/Date(1444021200000)/","EFLType":"BR","EFLLevel":1000,"EFLPrice":"13.90"},{"__metadata":{"id":"http://sapcmd02.retail.nrgenergy.com:8000/sap/opu/odata/sap/ZE_CCUX_CAMPAIGN_SRV/EFLS(EFLType='BR',EFLLevel=2000)","uri":"http://sapcmd02.retail.nrgenergy.com:8000/sap/opu/odata/sap/ZE_CCUX_CAMPAIGN_SRV/EFLS(EFLType='BR',EFLLevel=2000)","type":"ZE_CCUX_CAMPAIGN_OVW_SRV.EFL"},"Contract":"32253375","OfferCode":"50160442","StartDate":"/Date(1444021200000)/","EFLType":"BR","EFLLevel":2000,"EFLPrice":"13.50"}]},"Scripts":{"__deferred":{"uri":"http://sapcmd02.retail.nrgenergy.com:8000/sap/opu/odata/sap/ZE_CCUX_CAMPAIGN_SRV/CpgChgOfferS(Contract='32253375',OfferCode='50160442',StartDate=datetime'2015-10-05T05%3A00%3A00')/Scripts"}}}]}}