{"d":{"results":[{"__metadata":{"id":"http://sapcmd02.retail.nrgenergy.com:8000/sap/opu/odata/sap/ZE_CCUX_DPP_EXT_SRV/DPPCorresps(ContractAccountNumber='100738',PartnerID='64041')","uri":"http://sapcmd02.retail.nrgenergy.com:8000/sap/opu/odata/sap/ZE_CCUX_DPP_EXT_SRV/DPPCorresps(ContractAccountNumber='100738',PartnerID='64041')","type":"ZE_CCUX_DPP_EXT_SRV.DPPCorresp"},"Address":{"__metadata":{"type":"ZE_CCUX_DPP_EXT_SRV.Address"},"StandardFlag":"","co":"","Street":"Fannin St","HouseNo":"1211","UnitNo":"300","City":"Houston","State":"TX","ZipCode":"77479","PoBox":"","ShortForm":"","ValidFrom":null,"ValidTo":null,"Country":"","CityCode":"","Supplement":"","AddrLine":""},"ContractAccountNumber":"100738","PartnerID":"64041","Contract":"","eMail":"test@nrg.com","Fax":"713-345-9875","eMailCheck":null,"eAddrCheck":null,"FaxCheck":null}]}}